lazy_budget/__init__.py
lazy_budget/budget.py
lazy_budget/charts.py
lazy_budget/cli.py
lazy_budget/constants.py
lazy_budget/display.py
lazy_budget/functions.py
lazy_budget/helpers.py
lazy_budget/main.py
lazy_budget/money_provider.py
lazy_budget/stats.py
lazy_budget/__pycache__/__init__.cpython-39.pyc
lazy_budget/__pycache__/budget.cpython-39.pyc
lazy_budget/__pycache__/constants.cpython-39.pyc
lazy_budget-0.17.1.dist-info/METADATA
lazy_budget-0.17.1.dist-info/WHEEL
lazy_budget-0.17.1.dist-info/entry_points.txt
lazy_budget-0.17.1.dist-info/top_level.txt
lazy_budget-0.17.1.dist-info/RECORD
